{
  "enemies": {
    "forest_wolf": {
      "id": "forest_wolf",
      "name": "Forest Wolf",
      "nameCs": "Lesní vlk",
      "hp": 10,
      "atk": 3,
      "xp": 25,
      "goldMin": 8,
      "goldMax": 18,
      "difficulty": 5,
      "spriteKey": "wolves-only-transparent-sheet",
      "animPrefix": "wolf",
      "region": "verdant_forest"
    },
    "mushroom_giant": {
      "id": "mushroom_giant",
      "name": "Mushroom Giant",
      "nameCs": "Houbový obr",
      "hp": 12,
      "atk": 2,
      "xp": 35,
      "goldMin": 15,
      "goldMax": 25,
      "difficulty": 5,
      "spriteKey": "spritesheet--36--sheet",
      "animPrefix": "mushroom",
      "scale": 0.5,
      "region": "verdant_forest"
    },
    "thorn_sprite": {
      "id": "thorn_sprite",
      "name": "Thorn Sprite",
      "nameCs": "Trnový skřítek",
      "hp": 8,
      "atk": 4,
      "xp": 30,
      "goldMin": 12,
      "goldMax": 22,
      "difficulty": 6,
      "spriteKey": "forest-sprite",
      "region": "verdant_forest"
    },
    "elder_treant": {
      "id": "elder_treant",
      "name": "Elder Treant",
      "nameCs": "Prastarý ent",
      "hp": 20,
      "atk": 2,
      "defense": 1,
      "xp": 50,
      "goldMin": 25,
      "goldMax": 40,
      "difficulty": 7,
      "spriteKey": "spritesheet--37--sheet",
      "animPrefix": "treant",
      "scale": 0.5,
      "region": "verdant_forest"
    },
    "verdant_guardian": {
      "id": "verdant_guardian",
      "name": "Verdant Guardian",
      "nameCs": "Strážce lesa",
      "isBoss": true,
      "phases": [
        {
          "hp": 10,
          "atk": 2,
          "name": "Awakening",
          "nameCs": "Probuzení",
          "mathType": "addition",
          "mathDifficulty": 4,
          "ability": null,
          "healPercent": 30
        },
        {
          "hp": 10,
          "atk": 3,
          "name": "Fury",
          "nameCs": "Zuřivost",
          "mathType": "missing_operand",
          "mathDifficulty": 5,
          "ability": "vengeful_strike",
          "healPercent": 15
        },
        {
          "hp": 12,
          "atk": 3,
          "name": "Final Stand",
          "nameCs": "Poslední vzdor",
          "mathType": "comparison",
          "mathDifficulty": 6,
          "ability": "last_stand",
          "healPercent": 0
        }
      ],
      "phaseHealPlayer": 0,
      "xp": 150,
      "goldMin": 80,
      "goldMax": 120,
      "diamonds": 5,
      "difficulty": 8,
      "spriteKey": "forest-wolf",
      "region": "verdant_forest",
      "_note": "TODO: Replace with boss-guardian when art is ready"
    }
  }
}
